restack_integrations_openai/__init__.py
restack_integrations_openai/functions/__init__.py
restack_integrations_openai/functions/chat/__init__.py
restack_integrations_openai/functions/chat/completions_base.py
restack_integrations_openai/functions/chat/completions_stream.py
restack_integrations_openai/py.typed
restack_integrations_openai/service.py
restack_integrations_openai/task_queue.py
restack_integrations_openai/utils/__init__.py
restack_integrations_openai/utils/client.py
restack_integrations_openai/utils/cost.py
restack_integrations_openai-0.0.6.dist-info/METADATA
restack_integrations_openai-0.0.6.dist-info/WHEEL
restack_integrations_openai-0.0.6.dist-info/RECORD
